{"assets":{"D130F2C8C682871CE1E548A91CC54928":{"type":"texture","index":8,"assetRequest":{"type":"slide","state":"contents","slide":"none"},"url":{"native":"assets\/1DC7574F-0004-4A61-A739-906B6AE3D4E2.pdf"},"width":1920,"height":1080},"78DCFDC79466125F556552A5C0ED4ED7":{"type":"texture","index":6,"assetRequest":{"type":"slide","state":"contents","slide":"none"},"url":{"native":"assets\/1DC7574F-0004-4A61-A739-906B6AE3D4E2.pdf"},"width":735,"height":74},"82ABF33542CECB6A3099368921C9E819":{"type":"texture","index":3,"assetRequest":{"type":"slide","state":"contents","slide":"none"},"url":{"native":"assets\/1DC7574F-0004-4A61-A739-906B6AE3D4E2.pdf"},"width":427,"height":74},"CB56F0B3CF82F58DD490AF351BAAFC86":{"type":"texture","index":1,"assetRequest":{"type":"slide","state":"contents","slide":"none"},"url":{"native":"assets\/1DC7574F-0004-4A61-A739-906B6AE3D4E2.pdf"},"width":1337,"height":110},"E4ED9C930350BFB2E06DD59A2760DFAA":{"type":"texture","index":7,"assetRequest":{"type":"slide","state":"contents","slide":"none"},"url":{"native":"assets\/1DC7574F-0004-4A61-A739-906B6AE3D4E2.pdf"},"width":1920,"height":1080},"B7DA436456C233738E63454C42CFA678":{"type":"texture","index":4,"assetRequest":{"type":"slide","state":"contents","slide":"none"},"url":{"native":"assets\/1DC7574F-0004-4A61-A739-906B6AE3D4E2.pdf"},"width":189,"height":74},"ACD8C7F538D7B6317F7256BC3826AC83":{"type":"texture","index":0,"assetRequest":{"type":"slide","state":"contents","slide":"none"},"url":{"native":"assets\/1DC7574F-0004-4A61-A739-906B6AE3D4E2.pdf"},"width":1920,"height":1080},"047BA3E01BAFA95A6E2775B6BF8DBDBD":{"type":"texture","index":2,"assetRequest":{"type":"slide","state":"contents","slide":"none"},"url":{"native":"assets\/1DC7574F-0004-4A61-A739-906B6AE3D4E2.pdf"},"width":769,"height":74},"952DA6C4149651D70B7972DF03519E25":{"type":"texture","index":5,"assetRequest":{"type":"slide","state":"contents","slide":"none"},"url":{"native":"assets\/1DC7574F-0004-4A61-A739-906B6AE3D4E2.pdf"},"width":842,"height":74}},"events":[{"effects":[{"beginTime":0,"baseLayer":{"animations":[],"initialState":{"affineTransform":[1,0,0,1,0,0],"masksToBounds":false,"rotation":0,"scale":1,"position":{"pointX":554,"pointY":519},"width":842,"sublayerTransform":[1,0,0,0,0,1,0,0,0,0,1,0,0,0,0,1],"contentsRect":{"y":0,"x":0,"width":1,"height":1},"opacity":1,"edgeAntialiasingMask":251658240,"height":542,"hidden":false,"anchorPoint":{"pointX":0.5,"pointY":0.5}},"objectID":"4528A7A3-3462-44E6-9CB3-EDD9DBA676E9","layers":[{"animations":[],"initialState":{"affineTransform":[1,0,0,1,0,0],"masksToBounds":false,"rotation":0,"scale":1,"position":{"pointX":827,"pointY":292},"width":842,"sublayerTransform":[1,0,0,0,0,1,0,0,0,0,1,-0.0003500791246677598,0,0,0,1],"contentsRect":{"y":0,"x":0,"width":1,"height":1},"opacity":1,"edgeAntialiasingMask":251658240,"height":542,"hidden":false,"anchorPoint":{"pointX":0.9821852731591449,"pointY":0.5387453874538746}},"layers":[{"animations":[{"timeOffset":0,"beginTime":1e-100,"animations":[{"timeOffset":0,"from":{"scalar":0},"beginTime":0,"repeatCount":0,"fillMode":"both","duration":1,"autoreverses":false,"timingFunction":"EaseInEaseOut","property":"opacity","to":{"scalar":1}},{"timeOffset":0,"from":{"scalar":false},"beginTime":0,"repeatCount":0,"fillMode":"forwards","property":"hidden","autoreverses":false,"duration":1,"to":{"scalar":false}}],"repeatCount":0,"duration":1,"autoreverses":false,"fillMode":"both"}],"layers":[],"texturedRectangle":{"singleTextureOpacity":1,"textXHeight":0.3483243243243243,"textBaseline":0.7290807511355426,"isBackgroundTexture":false,"isVerticalText":false,"textColor":[0.9999966025352478,0.9999999403953552,0.9999999403953552,1],"textureType":6},"initialState":{"affineTransform":[1,0,0,1,0,0],"masksToBounds":false,"rotation":0,"scale":1,"position":{"pointX":388.5,"pointY":132},"width":769,"sublayerTransform":[1,0,0,0,0,1,0,0,0,0,1,0,0,0,0,1],"contentsRect":{"y":0,"x":0,"width":1,"height":1},"opacity":1,"edgeAntialiasingMask":0,"height":74,"hidden":true,"anchorPoint":{"pointX":0.5,"pointY":0.5}},"texture":"047BA3E01BAFA95A6E2775B6BF8DBDBD"}]},{"animations":[],"layers":[],"texturedRectangle":{"singleTextureOpacity":1,"textXHeight":0.3483243243243243,"textBaseline":0.7290807511355426,"isBackgroundTexture":false,"isVerticalText":false,"textColor":[0.9999966025352478,0.9999999403953552,0.9999999403953552,1],"textureType":6},"initialState":{"affineTransform":[1,0,0,1,0,0],"masksToBounds":false,"rotation":0,"scale":1,"position":{"pointX":217.5,"pointY":249},"width":427,"sublayerTransform":[1,0,0,0,0,1,0,0,0,0,1,0,0,0,0,1],"contentsRect":{"y":0,"x":0,"width":1,"height":1},"opacity":1,"edgeAntialiasingMask":0,"height":74,"hidden":true,"anchorPoint":{"pointX":0.5,"pointY":0.5}},"texture":"82ABF33542CECB6A3099368921C9E819"},{"animations":[],"layers":[],"texturedRectangle":{"singleTextureOpacity":1,"textXHeight":0.3483243243243243,"textBaseline":0.7290807511355426,"isBackgroundTexture":false,"isVerticalText":false,"textColor":[0.9999966025352478,0.9999999403953552,0.9999999403953552,1],"textureType":6},"initialState":{"affineTransform":[1,0,0,1,0,0],"masksToBounds":false,"rotation":0,"scale":1,"position":{"pointX":98.5,"pointY":366},"width":189,"sublayerTransform":[1,0,0,0,0,1,0,0,0,0,1,0,0,0,0,1],"contentsRect":{"y":0,"x":0,"width":1,"height":1},"opacity":1,"edgeAntialiasingMask":0,"height":74,"hidden":true,"anchorPoint":{"pointX":0.5,"pointY":0.5}},"texture":"B7DA436456C233738E63454C42CFA678"},{"animations":[],"layers":[],"texturedRectangle":{"singleTextureOpacity":1,"textXHeight":0.3483243243243243,"textBaseline":0.7290807511355426,"isBackgroundTexture":false,"isVerticalText":false,"textColor":[0.9999966025352478,0.9999999403953552,0.9999999403953552,1],"textureType":6},"initialState":{"affineTransform":[1,0,0,1,0,0],"masksToBounds":false,"rotation":0,"scale":1,"position":{"pointX":425,"pointY":483},"width":842,"sublayerTransform":[1,0,0,0,0,1,0,0,0,0,1,0,0,0,0,1],"contentsRect":{"y":0,"x":0,"width":1,"height":1},"opacity":1,"edgeAntialiasingMask":0,"height":74,"hidden":true,"anchorPoint":{"pointX":0.5,"pointY":0.5}},"texture":"952DA6C4149651D70B7972DF03519E25"},{"animations":[],"layers":[],"texturedRectangle":{"singleTextureOpacity":1,"textXHeight":0.3483243243243243,"textBaseline":0.7290807511355426,"isBackgroundTexture":false,"isVerticalText":false,"textColor":[0.9999966025352478,0.9999999403953552,0.9999999403953552,1],"textureType":6},"initialState":{"affineTransform":[1,0,0,1,0,0],"masksToBounds":false,"rotation":0,"scale":1,"position":{"pointX":371.5,"pointY":600},"width":735,"sublayerTransform":[1,0,0,0,0,1,0,0,0,0,1,0,0,0,0,1],"contentsRect":{"y":0,"x":0,"width":1,"height":1},"opacity":1,"edgeAntialiasingMask":0,"height":74,"hidden":true,"anchorPoint":{"pointX":0.5,"pointY":0.5}},"texture":"78DCFDC79466125F556552A5C0ED4ED7"}]},"effects":[],"duration":1,"type":"buildIn","name":"apple:dissolve character","objectID":"4528A7A3-3462-44E6-9CB3-EDD9DBA676E9"}],"automaticPlay":false,"hyperlinks":[],"accessibility":[{"text":"Avoid Being an @sshole","targetRectangle":{"y":50,"x":291.864,"width":1336.272,"height":136}}],"baseLayer":{"animations":[],"initialState":{"affineTransform":[1,0,0,1,0,0],"masksToBounds":false,"rotation":0,"scale":1,"position":{"pointX":960,"pointY":540},"width":1920,"sublayerTransform":[1,0,0,0,0,1,0,0,0,0,1,0,0,0,0,1],"contentsRect":{"y":0,"x":0,"width":1,"height":1},"opacity":1,"edgeAntialiasingMask":251658240,"height":1080,"hidden":false,"anchorPoint":{"pointX":0.5,"pointY":0.5}},"layers":[{"animations":[],"initialState":{"affineTransform":[1,0,0,1,0,0],"masksToBounds":false,"rotation":0,"scale":1,"position":{"pointX":960,"pointY":540},"width":1920,"sublayerTransform":[1,0,0,0,0,1,0,0,0,0,1,0,0,0,0,1],"contentsRect":{"y":0,"x":0,"width":1,"height":1},"opacity":1,"edgeAntialiasingMask":251658240,"height":1080,"hidden":false,"anchorPoint":{"pointX":0.5,"pointY":0.5}},"layers":[{"animations":[],"initialState":{"affineTransform":[1,0,0,1,0,0],"masksToBounds":false,"rotation":0,"scale":1,"position":{"pointX":960,"pointY":540},"width":1920,"sublayerTransform":[1,0,0,0,0,1,0,0,0,0,1,0,0,0,0,1],"contentsRect":{"y":0,"x":0,"width":1,"height":1},"opacity":1,"edgeAntialiasingMask":251658240,"height":1080,"hidden":false,"anchorPoint":{"pointX":0.5,"pointY":0.5}},"layers":[{"animations":[],"layers":[],"texturedRectangle":{"isBackgroundTexture":true,"singleTextureOpacity":1,"textureType":1,"textBaseline":0,"textXHeight":0,"isVerticalText":false},"initialState":{"affineTransform":[1,0,0,1,0,0],"masksToBounds":false,"rotation":0,"scale":1,"position":{"pointX":960,"pointY":540},"width":1920,"sublayerTransform":[1,0,0,0,0,1,0,0,0,0,1,0,0,0,0,1],"contentsRect":{"y":0,"x":0,"width":1,"height":1},"opacity":1,"edgeAntialiasingMask":0,"height":1080,"hidden":false,"anchorPoint":{"pointX":0.5,"pointY":0.5}},"texture":"ACD8C7F538D7B6317F7256BC3826AC83"}]}]},{"animations":[],"initialState":{"affineTransform":[1,0,0,1,0,0],"masksToBounds":false,"rotation":0,"scale":1,"position":{"pointX":960,"pointY":540},"width":1920,"sublayerTransform":[1,0,0,0,0,1,0,0,0,0,1,0,0,0,0,1],"contentsRect":{"y":0,"x":0,"width":1,"height":1},"opacity":1,"edgeAntialiasingMask":251658240,"height":1080,"hidden":false,"anchorPoint":{"pointX":0.5,"pointY":0.5}},"layers":[{"animations":[],"initialState":{"affineTransform":[1,0,0,1,0,0],"masksToBounds":false,"rotation":0,"scale":1,"position":{"pointX":801.5,"pointY":83},"width":1337,"sublayerTransform":[1,0,0,0,0,1,0,0,0,0,1,0,0,0,0,1],"contentsRect":{"y":0,"x":0,"width":1,"height":1},"opacity":1,"edgeAntialiasingMask":251658240,"height":110,"hidden":false,"anchorPoint":{"pointX":0.5,"pointY":0.5}},"layers":[{"animations":[],"layers":[],"texturedRectangle":{"singleTextureOpacity":1,"textXHeight":0.5467636363636363,"textBaseline":0.7807994820854881,"isBackgroundTexture":true,"isVerticalText":false,"textColor":[0.9999966025352478,0.9999999403953552,0.9999999403953552,1],"textureType":6},"initialState":{"affineTransform":[1,0,0,1,0,0],"masksToBounds":false,"rotation":0,"scale":1,"position":{"pointX":825.5,"pointY":99},"width":1337,"sublayerTransform":[1,0,0,0,0,1,0,0,0,0,1,0,0,0,0,1],"contentsRect":{"y":0,"x":0,"width":1,"height":1},"opacity":1,"edgeAntialiasingMask":0,"height":110,"hidden":false,"anchorPoint":{"pointX":0.5,"pointY":0.5}},"texture":"CB56F0B3CF82F58DD490AF351BAAFC86"}]}]},{"animations":[],"initialState":{"affineTransform":[1,0,0,1,0,0],"masksToBounds":false,"rotation":0,"scale":1,"position":{"pointX":960,"pointY":540},"width":1920,"sublayerTransform":[1,0,0,0,0,1,0,0,0,0,1,0,0,0,0,1],"contentsRect":{"y":0,"x":0,"width":1,"height":1},"opacity":1,"edgeAntialiasingMask":251658240,"height":1080,"hidden":false,"anchorPoint":{"pointX":0.5,"pointY":0.5}},"layers":[{"animations":[],"initialState":{"affineTransform":[1,0,0,1,0,0],"masksToBounds":false,"rotation":0,"scale":1,"position":{"pointX":554,"pointY":519},"width":842,"sublayerTransform":[1,0,0,0,0,1,0,0,0,0,1,0,0,0,0,1],"contentsRect":{"y":0,"x":0,"width":1,"height":1},"opacity":1,"edgeAntialiasingMask":251658240,"height":542,"hidden":false,"anchorPoint":{"pointX":0.5,"pointY":0.5}},"objectID":"4528A7A3-3462-44E6-9CB3-EDD9DBA676E9","layers":[{"animations":[],"layers":[],"texturedRectangle":{"singleTextureOpacity":1,"textXHeight":0.3483243243243243,"textBaseline":0.7290807511355426,"isBackgroundTexture":false,"isVerticalText":false,"textColor":[0.9999966025352478,0.9999999403953552,0.9999999403953552,1],"textureType":6},"initialState":{"affineTransform":[1,0,0,1,0,0],"masksToBounds":false,"rotation":0,"scale":1,"position":{"pointX":388.5,"pointY":132},"width":769,"sublayerTransform":[1,0,0,0,0,1,0,0,0,0,1,0,0,0,0,1],"contentsRect":{"y":0,"x":0,"width":1,"height":1},"opacity":1,"edgeAntialiasingMask":0,"height":74,"hidden":true,"anchorPoint":{"pointX":0.5,"pointY":0.5}},"texture":"047BA3E01BAFA95A6E2775B6BF8DBDBD"},{"animations":[],"layers":[],"texturedRectangle":{"singleTextureOpacity":1,"textXHeight":0.3483243243243243,"textBaseline":0.7290807511355426,"isBackgroundTexture":false,"isVerticalText":false,"textColor":[0.9999966025352478,0.9999999403953552,0.9999999403953552,1],"textureType":6},"initialState":{"affineTransform":[1,0,0,1,0,0],"masksToBounds":false,"rotation":0,"scale":1,"position":{"pointX":217.5,"pointY":249},"width":427,"sublayerTransform":[1,0,0,0,0,1,0,0,0,0,1,0,0,0,0,1],"contentsRect":{"y":0,"x":0,"width":1,"height":1},"opacity":1,"edgeAntialiasingMask":0,"height":74,"hidden":true,"anchorPoint":{"pointX":0.5,"pointY":0.5}},"texture":"82ABF33542CECB6A3099368921C9E819"},{"animations":[],"layers":[],"texturedRectangle":{"singleTextureOpacity":1,"textXHeight":0.3483243243243243,"textBaseline":0.7290807511355426,"isBackgroundTexture":false,"isVerticalText":false,"textColor":[0.9999966025352478,0.9999999403953552,0.9999999403953552,1],"textureType":6},"initialState":{"affineTransform":[1,0,0,1,0,0],"masksToBounds":false,"rotation":0,"scale":1,"position":{"pointX":98.5,"pointY":366},"width":189,"sublayerTransform":[1,0,0,0,0,1,0,0,0,0,1,0,0,0,0,1],"contentsRect":{"y":0,"x":0,"width":1,"height":1},"opacity":1,"edgeAntialiasingMask":0,"height":74,"hidden":true,"anchorPoint":{"pointX":0.5,"pointY":0.5}},"texture":"B7DA436456C233738E63454C42CFA678"},{"animations":[],"layers":[],"texturedRectangle":{"singleTextureOpacity":1,"textXHeight":0.3483243243243243,"textBaseline":0.7290807511355426,"isBackgroundTexture":false,"isVerticalText":false,"textColor":[0.9999966025352478,0.9999999403953552,0.9999999403953552,1],"textureType":6},"initialState":{"affineTransform":[1,0,0,1,0,0],"masksToBounds":false,"rotation":0,"scale":1,"position":{"pointX":425,"pointY":483},"width":842,"sublayerTransform":[1,0,0,0,0,1,0,0,0,0,1,0,0,0,0,1],"contentsRect":{"y":0,"x":0,"width":1,"height":1},"opacity":1,"edgeAntialiasingMask":0,"height":74,"hidden":true,"anchorPoint":{"pointX":0.5,"pointY":0.5}},"texture":"952DA6C4149651D70B7972DF03519E25"},{"animations":[],"layers":[],"texturedRectangle":{"singleTextureOpacity":1,"textXHeight":0.3483243243243243,"textBaseline":0.7290807511355426,"isBackgroundTexture":false,"isVerticalText":false,"textColor":[0.9999966025352478,0.9999999403953552,0.9999999403953552,1],"textureType":6},"initialState":{"affineTransform":[1,0,0,1,0,0],"masksToBounds":false,"rotation":0,"scale":1,"position":{"pointX":371.5,"pointY":600},"width":735,"sublayerTransform":[1,0,0,0,0,1,0,0,0,0,1,0,0,0,0,1],"contentsRect":{"y":0,"x":0,"width":1,"height":1},"opacity":1,"edgeAntialiasingMask":0,"height":74,"hidden":true,"anchorPoint":{"pointX":0.5,"pointY":0.5}},"texture":"78DCFDC79466125F556552A5C0ED4ED7"}]}]}]}},{"effects":[{"beginTime":0,"baseLayer":{"animations":[],"initialState":{"affineTransform":[1,0,0,1,0,0],"masksToBounds":false,"rotation":0,"scale":1,"position":{"pointX":554,"pointY":519},"width":842,"sublayerTransform":[1,0,0,0,0,1,0,0,0,0,1,0,0,0,0,1],"contentsRect":{"y":0,"x":0,"width":1,"height":1},"opacity":1,"edgeAntialiasingMask":251658240,"height":542,"hidden":false,"anchorPoint":{"pointX":0.5,"pointY":0.5}},"objectID":"4528A7A3-3462-44E6-9CB3-EDD9DBA676E9","layers":[{"animations":[],"layers":[],"texturedRectangle":{"singleTextureOpacity":1,"textXHeight":0.3483243243243243,"textBaseline":0.7290807511355426,"isBackgroundTexture":false,"isVerticalText":false,"textColor":[0.9999966025352478,0.9999999403953552,0.9999999403953552,1],"textureType":6},"initialState":{"affineTransform":[1,0,0,1,0,0],"masksToBounds":false,"rotation":0,"scale":1,"position":{"pointX":388.5,"pointY":132},"width":769,"sublayerTransform":[1,0,0,0,0,1,0,0,0,0,1,0,0,0,0,1],"contentsRect":{"y":0,"x":0,"width":1,"height":1},"opacity":1,"edgeAntialiasingMask":0,"height":74,"hidden":false,"anchorPoint":{"pointX":0.5,"pointY":0.5}},"texture":"047BA3E01BAFA95A6E2775B6BF8DBDBD"},{"animations":[],"initialState":{"affineTransform":[1,0,0,1,0,0],"masksToBounds":false,"rotation":0,"scale":1,"position":{"pointX":827,"pointY":292},"width":842,"sublayerTransform":[1,0,0,0,0,1,0,0,0,0,1,-0.0003500791246677598,0,0,0,1],"contentsRect":{"y":0,"x":0,"width":1,"height":1},"opacity":1,"edgeAntialiasingMask":251658240,"height":542,"hidden":false,"anchorPoint":{"pointX":0.9821852731591449,"pointY":0.5387453874538746}},"layers":[{"animations":[{"timeOffset":0,"beginTime":1e-100,"animations":[{"timeOffset":0,"from":{"scalar":0},"beginTime":0,"repeatCount":0,"fillMode":"both","duration":1,"autoreverses":false,"timingFunction":"EaseInEaseOut","property":"opacity","to":{"scalar":1}},{"timeOffset":0,"from":{"scalar":false},"beginTime":0,"repeatCount":0,"fillMode":"forwards","property":"hidden","autoreverses":false,"duration":1,"to":{"scalar":false}}],"repeatCount":0,"duration":1,"autoreverses":false,"fillMode":"both"}],"layers":[],"texturedRectangle":{"singleTextureOpacity":1,"textXHeight":0.3483243243243243,"textBaseline":0.7290807511355426,"isBackgroundTexture":false,"isVerticalText":false,"textColor":[0.9999966025352478,0.9999999403953552,0.9999999403953552,1],"textureType":6},"initialState":{"affineTransform":[1,0,0,1,0,0],"masksToBounds":false,"rotation":0,"scale":1,"position":{"pointX":217.5,"pointY":249},"width":427,"sublayerTransform":[1,0,0,0,0,1,0,0,0,0,1,0,0,0,0,1],"contentsRect":{"y":0,"x":0,"width":1,"height":1},"opacity":1,"edgeAntialiasingMask":0,"height":74,"hidden":true,"anchorPoint":{"pointX":0.5,"pointY":0.5}},"texture":"82ABF33542CECB6A3099368921C9E819"}]},{"animations":[],"layers":[],"texturedRectangle":{"singleTextureOpacity":1,"textXHeight":0.3483243243243243,"textBaseline":0.7290807511355426,"isBackgroundTexture":false,"isVerticalText":false,"textColor":[0.9999966025352478,0.9999999403953552,0.9999999403953552,1],"textureType":6},"initialState":{"affineTransform":[1,0,0,1,0,0],"masksToBounds":false,"rotation":0,"scale":1,"position":{"pointX":98.5,"pointY":366},"width":189,"sublayerTransform":[1,0,0,0,0,1,0,0,0,0,1,0,0,0,0,1],"contentsRect":{"y":0,"x":0,"width":1,"height":1},"opacity":1,"edgeAntialiasingMask":0,"height":74,"hidden":true,"anchorPoint":{"pointX":0.5,"pointY":0.5}},"texture":"B7DA436456C233738E63454C42CFA678"},{"animations":[],"layers":[],"texturedRectangle":{"singleTextureOpacity":1,"textXHeight":0.3483243243243243,"textBaseline":0.7290807511355426,"isBackgroundTexture":false,"isVerticalText":false,"textColor":[0.9999966025352478,0.9999999403953552,0.9999999403953552,1],"textureType":6},"initialState":{"affineTransform":[1,0,0,1,0,0],"masksToBounds":false,"rotation":0,"scale":1,"position":{"pointX":425,"pointY":483},"width":842,"sublayerTransform":[1,0,0,0,0,1,0,0,0,0,1,0,0,0,0,1],"contentsRect":{"y":0,"x":0,"width":1,"height":1},"opacity":1,"edgeAntialiasingMask":0,"height":74,"hidden":true,"anchorPoint":{"pointX":0.5,"pointY":0.5}},"texture":"952DA6C4149651D70B7972DF03519E25"},{"animations":[],"layers":[],"texturedRectangle":{"singleTextureOpacity":1,"textXHeight":0.3483243243243243,"textBaseline":0.7290807511355426,"isBackgroundTexture":false,"isVerticalText":false,"textColor":[0.9999966025352478,0.9999999403953552,0.9999999403953552,1],"textureType":6},"initialState":{"affineTransform":[1,0,0,1,0,0],"masksToBounds":false,"rotation":0,"scale":1,"position":{"pointX":371.5,"pointY":600},"width":735,"sublayerTransform":[1,0,0,0,0,1,0,0,0,0,1,0,0,0,0,1],"contentsRect":{"y":0,"x":0,"width":1,"height":1},"opacity":1,"edgeAntialiasingMask":0,"height":74,"hidden":true,"anchorPoint":{"pointX":0.5,"pointY":0.5}},"texture":"78DCFDC79466125F556552A5C0ED4ED7"}]},"effects":[],"duration":1,"type":"buildIn","name":"apple:dissolve character","objectID":"4528A7A3-3462-44E6-9CB3-EDD9DBA676E9"}],"automaticPlay":false,"hyperlinks":[],"accessibility":[{"text":"Support public, blame private","targetRectangle":{"y":351,"x":186.9999980926514,"width":718.3680000000002,"height":58}},{"text":"Avoid Being an @sshole","targetRectangle":{"y":50,"x":291.864,"width":1336.272,"height":136}}],"baseLayer":{"animations":[],"initialState":{"affineTransform":[1,0,0,1,0,0],"masksToBounds":false,"rotation":0,"scale":1,"position":{"pointX":960,"pointY":540},"width":1920,"sublayerTransform":[1,0,0,0,0,1,0,0,0,0,1,0,0,0,0,1],"contentsRect":{"y":0,"x":0,"width":1,"height":1},"opacity":1,"edgeAntialiasingMask":251658240,"height":1080,"hidden":false,"anchorPoint":{"pointX":0.5,"pointY":0.5}},"layers":[{"animations":[],"initialState":{"affineTransform":[1,0,0,1,0,0],"masksToBounds":false,"rotation":0,"scale":1,"position":{"pointX":960,"pointY":540},"width":1920,"sublayerTransform":[1,0,0,0,0,1,0,0,0,0,1,0,0,0,0,1],"contentsRect":{"y":0,"x":0,"width":1,"height":1},"opacity":1,"edgeAntialiasingMask":251658240,"height":1080,"hidden":false,"anchorPoint":{"pointX":0.5,"pointY":0.5}},"layers":[{"animations":[],"initialState":{"affineTransform":[1,0,0,1,0,0],"masksToBounds":false,"rotation":0,"scale":1,"position":{"pointX":960,"pointY":540},"width":1920,"sublayerTransform":[1,0,0,0,0,1,0,0,0,0,1,0,0,0,0,1],"contentsRect":{"y":0,"x":0,"width":1,"height":1},"opacity":1,"edgeAntialiasingMask":251658240,"height":1080,"hidden":false,"anchorPoint":{"pointX":0.5,"pointY":0.5}},"layers":[{"animations":[],"layers":[],"texturedRectangle":{"isBackgroundTexture":true,"singleTextureOpacity":1,"textureType":1,"textBaseline":0,"textXHeight":0,"isVerticalText":false},"initialState":{"affineTransform":[1,0,0,1,0,0],"masksToBounds":false,"rotation":0,"scale":1,"position":{"pointX":960,"pointY":540},"width":1920,"sublayerTransform":[1,0,0,0,0,1,0,0,0,0,1,0,0,0,0,1],"contentsRect":{"y":0,"x":0,"width":1,"height":1},"opacity":1,"edgeAntialiasingMask":0,"height":1080,"hidden":false,"anchorPoint":{"pointX":0.5,"pointY":0.5}},"texture":"ACD8C7F538D7B6317F7256BC3826AC83"}]}]},{"animations":[],"initialState":{"affineTransform":[1,0,0,1,0,0],"masksToBounds":false,"rotation":0,"scale":1,"position":{"pointX":960,"pointY":540},"width":1920,"sublayerTransform":[1,0,0,0,0,1,0,0,0,0,1,0,0,0,0,1],"contentsRect":{"y":0,"x":0,"width":1,"height":1},"opacity":1,"edgeAntialiasingMask":251658240,"height":1080,"hidden":false,"anchorPoint":{"pointX":0.5,"pointY":0.5}},"layers":[{"animations":[],"initialState":{"affineTransform":[1,0,0,1,0,0],"masksToBounds":false,"rotation":0,"scale":1,"position":{"pointX":801.5,"pointY":83},"width":1337,"sublayerTransform":[1,0,0,0,0,1,0,0,0,0,1,0,0,0,0,1],"contentsRect":{"y":0,"x":0,"width":1,"height":1},"opacity":1,"edgeAntialiasingMask":251658240,"height":110,"hidden":false,"anchorPoint":{"pointX":0.5,"pointY":0.5}},"layers":[{"animations":[],"layers":[],"texturedRectangle":{"singleTextureOpacity":1,"textXHeight":0.5467636363636363,"textBaseline":0.7807994820854881,"isBackgroundTexture":true,"isVerticalText":false,"textColor":[0.9999966025352478,0.9999999403953552,0.9999999403953552,1],"textureType":6},"initialState":{"affineTransform":[1,0,0,1,0,0],"masksToBounds":false,"rotation":0,"scale":1,"position":{"pointX":825.5,"pointY":99},"width":1337,"sublayerTransform":[1,0,0,0,0,1,0,0,0,0,1,0,0,0,0,1],"contentsRect":{"y":0,"x":0,"width":1,"height":1},"opacity":1,"edgeAntialiasingMask":0,"height":110,"hidden":false,"anchorPoint":{"pointX":0.5,"pointY":0.5}},"texture":"CB56F0B3CF82F58DD490AF351BAAFC86"}]}]},{"animations":[],"initialState":{"affineTransform":[1,0,0,1,0,0],"masksToBounds":false,"rotation":0,"scale":1,"position":{"pointX":960,"pointY":540},"width":1920,"sublayerTransform":[1,0,0,0,0,1,0,0,0,0,1,0,0,0,0,1],"contentsRect":{"y":0,"x":0,"width":1,"height":1},"opacity":1,"edgeAntialiasingMask":251658240,"height":1080,"hidden":false,"anchorPoint":{"pointX":0.5,"pointY":0.5}},"layers":[{"animations":[],"initialState":{"affineTransform":[1,0,0,1,0,0],"masksToBounds":false,"rotation":0,"scale":1,"position":{"pointX":554,"pointY":519},"width":842,"sublayerTransform":[1,0,0,0,0,1,0,0,0,0,1,0,0,0,0,1],"contentsRect":{"y":0,"x":0,"width":1,"height":1},"opacity":1,"edgeAntialiasingMask":251658240,"height":542,"hidden":false,"anchorPoint":{"pointX":0.5,"pointY":0.5}},"objectID":"4528A7A3-3462-44E6-9CB3-EDD9DBA676E9","layers":[{"animations":[],"layers":[],"texturedRectangle":{"singleTextureOpacity":1,"textXHeight":0.3483243243243243,"textBaseline":0.7290807511355426,"isBackgroundTexture":false,"isVerticalText":false,"textColor":[0.9999966025352478,0.9999999403953552,0.9999999403953552,1],"textureType":6},"initialState":{"affineTransform":[1,0,0,1,0,0],"masksToBounds":false,"rotation":0,"scale":1,"position":{"pointX":388.5,"pointY":132},"width":769,"sublayerTransform":[1,0,0,0,0,1,0,0,0,0,1,0,0,0,0,1],"contentsRect":{"y":0,"x":0,"width":1,"height":1},"opacity":1,"edgeAntialiasingMask":0,"height":74,"hidden":false,"anchorPoint":{"pointX":0.5,"pointY":0.5}},"texture":"047BA3E01BAFA95A6E2775B6BF8DBDBD"},{"animations":[],"layers":[],"texturedRectangle":{"singleTextureOpacity":1,"textXHeight":0.3483243243243243,"textBaseline":0.7290807511355426,"isBackgroundTexture":false,"isVerticalText":false,"textColor":[0.9999966025352478,0.9999999403953552,0.9999999403953552,1],"textureType":6},"initialState":{"affineTransform":[1,0,0,1,0,0],"masksToBounds":false,"rotation":0,"scale":1,"position":{"pointX":217.5,"pointY":249},"width":427,"sublayerTransform":[1,0,0,0,0,1,0,0,0,0,1,0,0,0,0,1],"contentsRect":{"y":0,"x":0,"width":1,"height":1},"opacity":1,"edgeAntialiasingMask":0,"height":74,"hidden":true,"anchorPoint":{"pointX":0.5,"pointY":0.5}},"texture":"82ABF33542CECB6A3099368921C9E819"},{"animations":[],"layers":[],"texturedRectangle":{"singleTextureOpacity":1,"textXHeight":0.3483243243243243,"textBaseline":0.7290807511355426,"isBackgroundTexture":false,"isVerticalText":false,"textColor":[0.9999966025352478,0.9999999403953552,0.9999999403953552,1],"textureType":6},"initialState":{"affineTransform":[1,0,0,1,0,0],"masksToBounds":false,"rotation":0,"scale":1,"position":{"pointX":98.5,"pointY":366},"width":189,"sublayerTransform":[1,0,0,0,0,1,0,0,0,0,1,0,0,0,0,1],"contentsRect":{"y":0,"x":0,"width":1,"height":1},"opacity":1,"edgeAntialiasingMask":0,"height":74,"hidden":true,"anchorPoint":{"pointX":0.5,"pointY":0.5}},"texture":"B7DA436456C233738E63454C42CFA678"},{"animations":[],"layers":[],"texturedRectangle":{"singleTextureOpacity":1,"textXHeight":0.3483243243243243,"textBaseline":0.7290807511355426,"isBackgroundTexture":false,"isVerticalText":false,"textColor":[0.9999966025352478,0.9999999403953552,0.9999999403953552,1],"textureType":6},"initialState":{"affineTransform":[1,0,0,1,0,0],"masksToBounds":false,"rotation":0,"scale":1,"position":{"pointX":425,"pointY":483},"width":842,"sublayerTransform":[1,0,0,0,0,1,0,0,0,0,1,0,0,0,0,1],"contentsRect":{"y":0,"x":0,"width":1,"height":1},"opacity":1,"edgeAntialiasingMask":0,"height":74,"hidden":true,"anchorPoint":{"pointX":0.5,"pointY":0.5}},"texture":"952DA6C4149651D70B7972DF03519E25"},{"animations":[],"layers":[],"texturedRectangle":{"singleTextureOpacity":1,"textXHeight":0.3483243243243243,"textBaseline":0.7290807511355426,"isBackgroundTexture":false,"isVerticalText":false,"textColor":[0.9999966025352478,0.9999999403953552,0.9999999403953552,1],"textureType":6},"initialState":{"affineTransform":[1,0,0,1,0,0],"masksToBounds":false,"rotation":0,"scale":1,"position":{"pointX":371.5,"pointY":600},"width":735,"sublayerTransform":[1,0,0,0,0,1,0,0,0,0,1,0,0,0,0,1],"contentsRect":{"y":0,"x":0,"width":1,"height":1},"opacity":1,"edgeAntialiasingMask":0,"height":74,"hidden":true,"anchorPoint":{"pointX":0.5,"pointY":0.5}},"texture":"78DCFDC79466125F556552A5C0ED4ED7"}]}]}]}},{"effects":[{"beginTime":0,"baseLayer":{"animations":[],"initialState":{"affineTransform":[1,0,0,1,0,0],"masksToBounds":false,"rotation":0,"scale":1,"position":{"pointX":554,"pointY":519},"width":842,"sublayerTransform":[1,0,0,0,0,1,0,0,0,0,1,0,0,0,0,1],"contentsRect":{"y":0,"x":0,"width":1,"height":1},"opacity":1,"edgeAntialiasingMask":251658240,"height":542,"hidden":false,"anchorPoint":{"pointX":0.5,"pointY":0.5}},"objectID":"4528A7A3-3462-44E6-9CB3-EDD9DBA676E9","layers":[{"animations":[],"layers":[],"texturedRectangle":{"singleTextureOpacity":1,"textXHeight":0.3483243243243243,"textBaseline":0.7290807511355426,"isBackgroundTexture":false,"isVerticalText":false,"textColor":[0.9999966025352478,0.9999999403953552,0.9999999403953552,1],"textureType":6},"initialState":{"affineTransform":[1,0,0,1,0,0],"masksToBounds":false,"rotation":0,"scale":1,"position":{"pointX":388.5,"pointY":132},"width":769,"sublayerTransform":[1,0,0,0,0,1,0,0,0,0,1,0,0,0,0,1],"contentsRect":{"y":0,"x":0,"width":1,"height":1},"opacity":1,"edgeAntialiasingMask":0,"height":74,"hidden":false,"anchorPoint":{"pointX":0.5,"pointY":0.5}},"texture":"047BA3E01BAFA95A6E2775B6BF8DBDBD"},{"animations":[],"layers":[],"texturedRectangle":{"singleTextureOpacity":1,"textXHeight":0.3483243243243243,"textBaseline":0.7290807511355426,"isBackgroundTexture":false,"isVerticalText":false,"textColor":[0.9999966025352478,0.9999999403953552,0.9999999403953552,1],"textureType":6},"initialState":{"affineTransform":[1,0,0,1,0,0],"masksToBounds":false,"rotation":0,"scale":1,"position":{"pointX":217.5,"pointY":249},"width":427,"sublayerTransform":[1,0,0,0,0,1,0,0,0,0,1,0,0,0,0,1],"contentsRect":{"y":0,"x":0,"width":1,"height":1},"opacity":1,"edgeAntialiasingMask":0,"height":74,"hidden":false,"anchorPoint":{"pointX":0.5,"pointY":0.5}},"texture":"82ABF33542CECB6A3099368921C9E819"},{"animations":[],"initialState":{"affineTransform":[1,0,0,1,0,0],"masksToBounds":false,"rotation":0,"scale":1,"position":{"pointX":827,"pointY":292},"width":842,"sublayerTransform":[1,0,0,0,0,1,0,0,0,0,1,-0.0003500791246677598,0,0,0,1],"contentsRect":{"y":0,"x":0,"width":1,"height":1},"opacity":1,"edgeAntialiasingMask":251658240,"height":542,"hidden":false,"anchorPoint":{"pointX":0.9821852731591449,"pointY":0.5387453874538746}},"layers":[{"animations":[{"timeOffset":0,"beginTime":1e-100,"animations":[{"timeOffset":0,"from":{"scalar":0},"beginTime":0,"repeatCount":0,"fillMode":"both","duration":1,"autoreverses":false,"timingFunction":"EaseInEaseOut","property":"opacity","to":{"scalar":1}},{"timeOffset":0,"from":{"scalar":false},"beginTime":0,"repeatCount":0,"fillMode":"forwards","property":"hidden","autoreverses":false,"duration":1,"to":{"scalar":false}}],"repeatCount":0,"duration":1,"autoreverses":false,"fillMode":"both"}],"layers":[],"texturedRectangle":{"singleTextureOpacity":1,"textXHeight":0.3483243243243243,"textBaseline":0.7290807511355426,"isBackgroundTexture":false,"isVerticalText":false,"textColor":[0.9999966025352478,0.9999999403953552,0.9999999403953552,1],"textureType":6},"initialState":{"affineTransform":[1,0,0,1,0,0],"masksToBounds":false,"rotation":0,"scale":1,"position":{"pointX":98.5,"pointY":366},"width":189,"sublayerTransform":[1,0,0,0,0,1,0,0,0,0,1,0,0,0,0,1],"contentsRect":{"y":0,"x":0,"width":1,"height":1},"opacity":1,"edgeAntialiasingMask":0,"height":74,"hidden":true,"anchorPoint":{"pointX":0.5,"pointY":0.5}},"texture":"B7DA436456C233738E63454C42CFA678"}]},{"animations":[],"layers":[],"texturedRectangle":{"singleTextureOpacity":1,"textXHeight":0.3483243243243243,"textBaseline":0.7290807511355426,"isBackgroundTexture":false,"isVerticalText":false,"textColor":[0.9999966025352478,0.9999999403953552,0.9999999403953552,1],"textureType":6},"initialState":{"affineTransform":[1,0,0,1,0,0],"masksToBounds":false,"rotation":0,"scale":1,"position":{"pointX":425,"pointY":483},"width":842,"sublayerTransform":[1,0,0,0,0,1,0,0,0,0,1,0,0,0,0,1],"contentsRect":{"y":0,"x":0,"width":1,"height":1},"opacity":1,"edgeAntialiasingMask":0,"height":74,"hidden":true,"anchorPoint":{"pointX":0.5,"pointY":0.5}},"texture":"952DA6C4149651D70B7972DF03519E25"},{"animations":[],"layers":[],"texturedRectangle":{"singleTextureOpacity":1,"textXHeight":0.3483243243243243,"textBaseline":0.7290807511355426,"isBackgroundTexture":false,"isVerticalText":false,"textColor":[0.9999966025352478,0.9999999403953552,0.9999999403953552,1],"textureType":6},"initialState":{"affineTransform":[1,0,0,1,0,0],"masksToBounds":false,"rotation":0,"scale":1,"position":{"pointX":371.5,"pointY":600},"width":735,"sublayerTransform":[1,0,0,0,0,1,0,0,0,0,1,0,0,0,0,1],"contentsRect":{"y":0,"x":0,"width":1,"height":1},"opacity":1,"edgeAntialiasingMask":0,"height":74,"hidden":true,"anchorPoint":{"pointX":0.5,"pointY":0.5}},"texture":"78DCFDC79466125F556552A5C0ED4ED7"}]},"effects":[],"duration":1,"type":"buildIn","name":"apple:dissolve character","objectID":"4528A7A3-3462-44E6-9CB3-EDD9DBA676E9"}],"automaticPlay":false,"hyperlinks":[],"accessibility":[{"text":"Support public, blame private","targetRectangle":{"y":351,"x":186.9999980926514,"width":718.3680000000002,"height":58}},{"text":"Admit mistakes","targetRectangle":{"y":409,"x":186.9999980926514,"width":376.6079999999999,"height":117}},{"text":"Avoid Being an @sshole","targetRectangle":{"y":50,"x":291.864,"width":1336.272,"height":136}}],"baseLayer":{"animations":[],"initialState":{"affineTransform":[1,0,0,1,0,0],"masksToBounds":false,"rotation":0,"scale":1,"position":{"pointX":960,"pointY":540},"width":1920,"sublayerTransform":[1,0,0,0,0,1,0,0,0,0,1,0,0,0,0,1],"contentsRect":{"y":0,"x":0,"width":1,"height":1},"opacity":1,"edgeAntialiasingMask":251658240,"height":1080,"hidden":false,"anchorPoint":{"pointX":0.5,"pointY":0.5}},"layers":[{"animations":[],"initialState":{"affineTransform":[1,0,0,1,0,0],"masksToBounds":false,"rotation":0,"scale":1,"position":{"pointX":960,"pointY":540},"width":1920,"sublayerTransform":[1,0,0,0,0,1,0,0,0,0,1,0,0,0,0,1],"contentsRect":{"y":0,"x":0,"width":1,"height":1},"opacity":1,"edgeAntialiasingMask":251658240,"height":1080,"hidden":false,"anchorPoint":{"pointX":0.5,"pointY":0.5}},"layers":[{"animations":[],"initialState":{"affineTransform":[1,0,0,1,0,0],"masksToBounds":false,"rotation":0,"scale":1,"position":{"pointX":960,"pointY":540},"width":1920,"sublayerTransform":[1,0,0,0,0,1,0,0,0,0,1,0,0,0,0,1],"contentsRect":{"y":0,"x":0,"width":1,"height":1},"opacity":1,"edgeAntialiasingMask":251658240,"height":1080,"hidden":false,"anchorPoint":{"pointX":0.5,"pointY":0.5}},"layers":[{"animations":[],"layers":[],"texturedRectangle":{"isBackgroundTexture":true,"singleTextureOpacity":1,"textureType":1,"textBaseline":0,"textXHeight":0,"isVerticalText":false},"initialState":{"affineTransform":[1,0,0,1,0,0],"masksToBounds":false,"rotation":0,"scale":1,"position":{"pointX":960,"pointY":540},"width":1920,"sublayerTransform":[1,0,0,0,0,1,0,0,0,0,1,0,0,0,0,1],"contentsRect":{"y":0,"x":0,"width":1,"height":1},"opacity":1,"edgeAntialiasingMask":0,"height":1080,"hidden":false,"anchorPoint":{"pointX":0.5,"pointY":0.5}},"texture":"ACD8C7F538D7B6317F7256BC3826AC83"}]}]},{"animations":[],"initialState":{"affineTransform":[1,0,0,1,0,0],"masksToBounds":false,"rotation":0,"scale":1,"position":{"pointX":960,"pointY":540},"width":1920,"sublayerTransform":[1,0,0,0,0,1,0,0,0,0,1,0,0,0,0,1],"contentsRect":{"y":0,"x":0,"width":1,"height":1},"opacity":1,"edgeAntialiasingMask":251658240,"height":1080,"hidden":false,"anchorPoint":{"pointX":0.5,"pointY":0.5}},"layers":[{"animations":[],"initialState":{"affineTransform":[1,0,0,1,0,0],"masksToBounds":false,"rotation":0,"scale":1,"position":{"pointX":801.5,"pointY":83},"width":1337,"sublayerTransform":[1,0,0,0,0,1,0,0,0,0,1,0,0,0,0,1],"contentsRect":{"y":0,"x":0,"width":1,"height":1},"opacity":1,"edgeAntialiasingMask":251658240,"height":110,"hidden":false,"anchorPoint":{"pointX":0.5,"pointY":0.5}},"layers":[{"animations":[],"layers":[],"texturedRectangle":{"singleTextureOpacity":1,"textXHeight":0.5467636363636363,"textBaseline":0.7807994820854881,"isBackgroundTexture":true,"isVerticalText":false,"textColor":[0.9999966025352478,0.9999999403953552,0.9999999403953552,1],"textureType":6},"initialState":{"affineTransform":[1,0,0,1,0,0],"masksToBounds":false,"rotation":0,"scale":1,"position":{"pointX":825.5,"pointY":99},"width":1337,"sublayerTransform":[1,0,0,0,0,1,0,0,0,0,1,0,0,0,0,1],"contentsRect":{"y":0,"x":0,"width":1,"height":1},"opacity":1,"edgeAntialiasingMask":0,"height":110,"hidden":false,"anchorPoint":{"pointX":0.5,"pointY":0.5}},"texture":"CB56F0B3CF82F58DD490AF351BAAFC86"}]}]},{"animations":[],"initialState":{"affineTransform":[1,0,0,1,0,0],"masksToBounds":false,"rotation":0,"scale":1,"position":{"pointX":960,"pointY":540},"width":1920,"sublayerTransform":[1,0,0,0,0,1,0,0,0,0,1,0,0,0,0,1],"contentsRect":{"y":0,"x":0,"width":1,"height":1},"opacity":1,"edgeAntialiasingMask":251658240,"height":1080,"hidden":false,"anchorPoint":{"pointX":0.5,"pointY":0.5}},"layers":[{"animations":[],"initialState":{"affineTransform":[1,0,0,1,0,0],"masksToBounds":false,"rotation":0,"scale":1,"position":{"pointX":554,"pointY":519},"width":842,"sublayerTransform":[1,0,0,0,0,1,0,0,0,0,1,0,0,0,0,1],"contentsRect":{"y":0,"x":0,"width":1,"height":1},"opacity":1,"edgeAntialiasingMask":251658240,"height":542,"hidden":false,"anchorPoint":{"pointX":0.5,"pointY":0.5}},"objectID":"4528A7A3-3462-44E6-9CB3-EDD9DBA676E9","layers":[{"animations":[],"layers":[],"texturedRectangle":{"singleTextureOpacity":1,"textXHeight":0.3483243243243243,"textBaseline":0.7290807511355426,"isBackgroundTexture":false,"isVerticalText":false,"textColor":[0.9999966025352478,0.9999999403953552,0.9999999403953552,1],"textureType":6},"initialState":{"affineTransform":[1,0,0,1,0,0],"masksToBounds":false,"rotation":0,"scale":1,"position":{"pointX":388.5,"pointY":132},"width":769,"sublayerTransform":[1,0,0,0,0,1,0,0,0,0,1,0,0,0,0,1],"contentsRect":{"y":0,"x":0,"width":1,"height":1},"opacity":1,"edgeAntialiasingMask":0,"height":74,"hidden":false,"anchorPoint":{"pointX":0.5,"pointY":0.5}},"texture":"047BA3E01BAFA95A6E2775B6BF8DBDBD"},{"animations":[],"layers":[],"texturedRectangle":{"singleTextureOpacity":1,"textXHeight":0.3483243243243243,"textBaseline":0.7290807511355426,"isBackgroundTexture":false,"isVerticalText":false,"textColor":[0.9999966025352478,0.9999999403953552,0.9999999403953552,1],"textureType":6},"initialState":{"affineTransform":[1,0,0,1,0,0],"masksToBounds":false,"rotation":0,"scale":1,"position":{"pointX":217.5,"pointY":249},"width":427,"sublayerTransform":[1,0,0,0,0,1,0,0,0,0,1,0,0,0,0,1],"contentsRect":{"y":0,"x":0,"width":1,"height":1},"opacity":1,"edgeAntialiasingMask":0,"height":74,"hidden":false,"anchorPoint":{"pointX":0.5,"pointY":0.5}},"texture":"82ABF33542CECB6A3099368921C9E819"},{"animations":[],"layers":[],"texturedRectangle":{"singleTextureOpacity":1,"textXHeight":0.3483243243243243,"textBaseline":0.7290807511355426,"isBackgroundTexture":false,"isVerticalText":false,"textColor":[0.9999966025352478,0.9999999403953552,0.9999999403953552,1],"textureType":6},"initialState":{"affineTransform":[1,0,0,1,0,0],"masksToBounds":false,"rotation":0,"scale":1,"position":{"pointX":98.5,"pointY":366},"width":189,"sublayerTransform":[1,0,0,0,0,1,0,0,0,0,1,0,0,0,0,1],"contentsRect":{"y":0,"x":0,"width":1,"height":1},"opacity":1,"edgeAntialiasingMask":0,"height":74,"hidden":true,"anchorPoint":{"pointX":0.5,"pointY":0.5}},"texture":"B7DA436456C233738E63454C42CFA678"},{"animations":[],"layers":[],"texturedRectangle":{"singleTextureOpacity":1,"textXHeight":0.3483243243243243,"textBaseline":0.7290807511355426,"isBackgroundTexture":false,"isVerticalText":false,"textColor":[0.9999966025352478,0.9999999403953552,0.9999999403953552,1],"textureType":6},"initialState":{"affineTransform":[1,0,0,1,0,0],"masksToBounds":false,"rotation":0,"scale":1,"position":{"pointX":425,"pointY":483},"width":842,"sublayerTransform":[1,0,0,0,0,1,0,0,0,0,1,0,0,0,0,1],"contentsRect":{"y":0,"x":0,"width":1,"height":1},"opacity":1,"edgeAntialiasingMask":0,"height":74,"hidden":true,"anchorPoint":{"pointX":0.5,"pointY":0.5}},"texture":"952DA6C4149651D70B7972DF03519E25"},{"animations":[],"layers":[],"texturedRectangle":{"singleTextureOpacity":1,"textXHeight":0.3483243243243243,"textBaseline":0.7290807511355426,"isBackgroundTexture":false,"isVerticalText":false,"textColor":[0.9999966025352478,0.9999999403953552,0.9999999403953552,1],"textureType":6},"initialState":{"affineTransform":[1,0,0,1,0,0],"masksToBounds":false,"rotation":0,"scale":1,"position":{"pointX":371.5,"pointY":600},"width":735,"sublayerTransform":[1,0,0,0,0,1,0,0,0,0,1,0,0,0,0,1],"contentsRect":{"y":0,"x":0,"width":1,"height":1},"opacity":1,"edgeAntialiasingMask":0,"height":74,"hidden":true,"anchorPoint":{"pointX":0.5,"pointY":0.5}},"texture":"78DCFDC79466125F556552A5C0ED4ED7"}]}]}]}},{"effects":[{"beginTime":0,"baseLayer":{"animations":[],"initialState":{"affineTransform":[1,0,0,1,0,0],"masksToBounds":false,"rotation":0,"scale":1,"position":{"pointX":554,"pointY":519},"width":842,"sublayerTransform":[1,0,0,0,0,1,0,0,0,0,1,0,0,0,0,1],"contentsRect":{"y":0,"x":0,"width":1,"height":1},"opacity":1,"edgeAntialiasingMask":251658240,"height":542,"hidden":false,"anchorPoint":{"pointX":0.5,"pointY":0.5}},"objectID":"4528A7A3-3462-44E6-9CB3-EDD9DBA676E9","layers":[{"animations":[],"layers":[],"texturedRectangle":{"singleTextureOpacity":1,"textXHeight":0.3483243243243243,"textBaseline":0.7290807511355426,"isBackgroundTexture":false,"isVerticalText":false,"textColor":[0.9999966025352478,0.9999999403953552,0.9999999403953552,1],"textureType":6},"initialState":{"affineTransform":[1,0,0,1,0,0],"masksToBounds":false,"rotation":0,"scale":1,"position":{"pointX":388.5,"pointY":132},"width":769,"sublayerTransform":[1,0,0,0,0,1,0,0,0,0,1,0,0,0,0,1],"contentsRect":{"y":0,"x":0,"width":1,"height":1},"opacity":1,"edgeAntialiasingMask":0,"height":74,"hidden":false,"anchorPoint":{"pointX":0.5,"pointY":0.5}},"texture":"047BA3E01BAFA95A6E2775B6BF8DBDBD"},{"animations":[],"layers":[],"texturedRectangle":{"singleTextureOpacity":1,"textXHeight":0.3483243243243243,"textBaseline":0.7290807511355426,"isBackgroundTexture":false,"isVerticalText":false,"textColor":[0.9999966025352478,0.9999999403953552,0.9999999403953552,1],"textureType":6},"initialState":{"affineTransform":[1,0,0,1,0,0],"masksToBounds":false,"rotation":0,"scale":1,"position":{"pointX":217.5,"pointY":249},"width":427,"sublayerTransform":[1,0,0,0,0,1,0,0,0,0,1,0,0,0,0,1],"contentsRect":{"y":0,"x":0,"width":1,"height":1},"opacity":1,"edgeAntialiasingMask":0,"height":74,"hidden":false,"anchorPoint":{"pointX":0.5,"pointY":0.5}},"texture":"82ABF33542CECB6A3099368921C9E819"},{"animations":[],"layers":[],"texturedRectangle":{"singleTextureOpacity":1,"textXHeight":0.3483243243243243,"textBaseline":0.7290807511355426,"isBackgroundTexture":false,"isVerticalText":false,"textColor":[0.9999966025352478,0.9999999403953552,0.9999999403953552,1],"textureType":6},"initialState":{"affineTransform":[1,0,0,1,0,0],"masksToBounds":false,"rotation":0,"scale":1,"position":{"pointX":98.5,"pointY":366},"width":189,"sublayerTransform":[1,0,0,0,0,1,0,0,0,0,1,0,0,0,0,1],"contentsRect":{"y":0,"x":0,"width":1,"height":1},"opacity":1,"edgeAntialiasingMask":0,"height":74,"hidden":false,"anchorPoint":{"pointX":0.5,"pointY":0.5}},"texture":"B7DA436456C233738E63454C42CFA678"},{"animations":[],"initialState":{"affineTransform":[1,0,0,1,0,0],"masksToBounds":false,"rotation":0,"scale":1,"position":{"pointX":827,"pointY":292},"width":842,"sublayerTransform":[1,0,0,0,0,1,0,0,0,0,1,-0.0003500791246677598,0,0,0,1],"contentsRect":{"y":0,"x":0,"width":1,"height":1},"opacity":1,"edgeAntialiasingMask":251658240,"height":542,"hidden":false,"anchorPoint":{"pointX":0.9821852731591449,"pointY":0.5387453874538746}},"layers":[{"animations":[{"timeOffset":0,"beginTime":1e-100,"animations":[{"timeOffset":0,"from":{"scalar":0},"beginTime":0,"repeatCount":0,"fillMode":"both","duration":1,"autoreverses":false,"timingFunction":"EaseInEaseOut","property":"opacity","to":{"scalar":1}},{"timeOffset":0,"from":{"scalar":false},"beginTime":0,"repeatCount":0,"fillMode":"forwards","property":"hidden","autoreverses":false,"duration":1,"to":{"scalar":false}}],"repeatCount":0,"duration":1,"autoreverses":false,"fillMode":"both"}],"layers":[],"texturedRectangle":{"singleTextureOpacity":1,"textXHeight":0.3483243243243243,"textBaseline":0.7290807511355426,"isBackgroundTexture":false,"isVerticalText":false,"textColor":[0.9999966025352478,0.9999999403953552,0.9999999403953552,1],"textureType":6},"initialState":{"affineTransform":[1,0,0,1,0,0],"masksToBounds":false,"rotation":0,"scale":1,"position":{"pointX":425,"pointY":483},"width":842,"sublayerTransform":[1,0,0,0,0,1,0,0,0,0,1,0,0,0,0,1],"contentsRect":{"y":0,"x":0,"width":1,"height":1},"opacity":1,"edgeAntialiasingMask":0,"height":74,"hidden":true,"anchorPoint":{"pointX":0.5,"pointY":0.5}},"texture":"952DA6C4149651D70B7972DF03519E25"}]},{"animations":[],"layers":[],"texturedRectangle":{"singleTextureOpacity":1,"textXHeight":0.3483243243243243,"textBaseline":0.7290807511355426,"isBackgroundTexture":false,"isVerticalText":false,"textColor":[0.9999966025352478,0.9999999403953552,0.9999999403953552,1],"textureType":6},"initialState":{"affineTransform":[1,0,0,1,0,0],"masksToBounds":false,"rotation":0,"scale":1,"position":{"pointX":371.5,"pointY":600},"width":735,"sublayerTransform":[1,0,0,0,0,1,0,0,0,0,1,0,0,0,0,1],"contentsRect":{"y":0,"x":0,"width":1,"height":1},"opacity":1,"edgeAntialiasingMask":0,"height":74,"hidden":true,"anchorPoint":{"pointX":0.5,"pointY":0.5}},"texture":"78DCFDC79466125F556552A5C0ED4ED7"}]},"effects":[],"duration":1,"type":"buildIn","name":"apple:dissolve character","objectID":"4528A7A3-3462-44E6-9CB3-EDD9DBA676E9"}],"automaticPlay":false,"hyperlinks":[],"accessibility":[{"text":"Support public, blame private","targetRectangle":{"y":351,"x":186.9999980926514,"width":718.3680000000002,"height":58}},{"text":"Admit mistakes","targetRectangle":{"y":409,"x":186.9999980926514,"width":376.6079999999999,"height":117}},{"text":"Listen","targetRectangle":{"y":526,"x":186.9999980926514,"width":141.12,"height":117}},{"text":"Avoid Being an @sshole","targetRectangle":{"y":50,"x":291.864,"width":1336.272,"height":136}}],"baseLayer":{"animations":[],"initialState":{"affineTransform":[1,0,0,1,0,0],"masksToBounds":false,"rotation":0,"scale":1,"position":{"pointX":960,"pointY":540},"width":1920,"sublayerTransform":[1,0,0,0,0,1,0,0,0,0,1,0,0,0,0,1],"contentsRect":{"y":0,"x":0,"width":1,"height":1},"opacity":1,"edgeAntialiasingMask":251658240,"height":1080,"hidden":false,"anchorPoint":{"pointX":0.5,"pointY":0.5}},"layers":[{"animations":[],"initialState":{"affineTransform":[1,0,0,1,0,0],"masksToBounds":false,"rotation":0,"scale":1,"position":{"pointX":960,"pointY":540},"width":1920,"sublayerTransform":[1,0,0,0,0,1,0,0,0,0,1,0,0,0,0,1],"contentsRect":{"y":0,"x":0,"width":1,"height":1},"opacity":1,"edgeAntialiasingMask":251658240,"height":1080,"hidden":false,"anchorPoint":{"pointX":0.5,"pointY":0.5}},"layers":[{"animations":[],"initialState":{"affineTransform":[1,0,0,1,0,0],"masksToBounds":false,"rotation":0,"scale":1,"position":{"pointX":960,"pointY":540},"width":1920,"sublayerTransform":[1,0,0,0,0,1,0,0,0,0,1,0,0,0,0,1],"contentsRect":{"y":0,"x":0,"width":1,"height":1},"opacity":1,"edgeAntialiasingMask":251658240,"height":1080,"hidden":false,"anchorPoint":{"pointX":0.5,"pointY":0.5}},"layers":[{"animations":[],"layers":[],"texturedRectangle":{"isBackgroundTexture":true,"singleTextureOpacity":1,"textureType":1,"textBaseline":0,"textXHeight":0,"isVerticalText":false},"initialState":{"affineTransform":[1,0,0,1,0,0],"masksToBounds":false,"rotation":0,"scale":1,"position":{"pointX":960,"pointY":540},"width":1920,"sublayerTransform":[1,0,0,0,0,1,0,0,0,0,1,0,0,0,0,1],"contentsRect":{"y":0,"x":0,"width":1,"height":1},"opacity":1,"edgeAntialiasingMask":0,"height":1080,"hidden":false,"anchorPoint":{"pointX":0.5,"pointY":0.5}},"texture":"ACD8C7F538D7B6317F7256BC3826AC83"}]}]},{"animations":[],"initialState":{"affineTransform":[1,0,0,1,0,0],"masksToBounds":false,"rotation":0,"scale":1,"position":{"pointX":960,"pointY":540},"width":1920,"sublayerTransform":[1,0,0,0,0,1,0,0,0,0,1,0,0,0,0,1],"contentsRect":{"y":0,"x":0,"width":1,"height":1},"opacity":1,"edgeAntialiasingMask":251658240,"height":1080,"hidden":false,"anchorPoint":{"pointX":0.5,"pointY":0.5}},"layers":[{"animations":[],"initialState":{"affineTransform":[1,0,0,1,0,0],"masksToBounds":false,"rotation":0,"scale":1,"position":{"pointX":801.5,"pointY":83},"width":1337,"sublayerTransform":[1,0,0,0,0,1,0,0,0,0,1,0,0,0,0,1],"contentsRect":{"y":0,"x":0,"width":1,"height":1},"opacity":1,"edgeAntialiasingMask":251658240,"height":110,"hidden":false,"anchorPoint":{"pointX":0.5,"pointY":0.5}},"layers":[{"animations":[],"layers":[],"texturedRectangle":{"singleTextureOpacity":1,"textXHeight":0.5467636363636363,"textBaseline":0.7807994820854881,"isBackgroundTexture":true,"isVerticalText":false,"textColor":[0.9999966025352478,0.9999999403953552,0.9999999403953552,1],"textureType":6},"initialState":{"affineTransform":[1,0,0,1,0,0],"masksToBounds":false,"rotation":0,"scale":1,"position":{"pointX":825.5,"pointY":99},"width":1337,"sublayerTransform":[1,0,0,0,0,1,0,0,0,0,1,0,0,0,0,1],"contentsRect":{"y":0,"x":0,"width":1,"height":1},"opacity":1,"edgeAntialiasingMask":0,"height":110,"hidden":false,"anchorPoint":{"pointX":0.5,"pointY":0.5}},"texture":"CB56F0B3CF82F58DD490AF351BAAFC86"}]}]},{"animations":[],"initialState":{"affineTransform":[1,0,0,1,0,0],"masksToBounds":false,"rotation":0,"scale":1,"position":{"pointX":960,"pointY":540},"width":1920,"sublayerTransform":[1,0,0,0,0,1,0,0,0,0,1,0,0,0,0,1],"contentsRect":{"y":0,"x":0,"width":1,"height":1},"opacity":1,"edgeAntialiasingMask":251658240,"height":1080,"hidden":false,"anchorPoint":{"pointX":0.5,"pointY":0.5}},"layers":[{"animations":[],"initialState":{"affineTransform":[1,0,0,1,0,0],"masksToBounds":false,"rotation":0,"scale":1,"position":{"pointX":554,"pointY":519},"width":842,"sublayerTransform":[1,0,0,0,0,1,0,0,0,0,1,0,0,0,0,1],"contentsRect":{"y":0,"x":0,"width":1,"height":1},"opacity":1,"edgeAntialiasingMask":251658240,"height":542,"hidden":false,"anchorPoint":{"pointX":0.5,"pointY":0.5}},"objectID":"4528A7A3-3462-44E6-9CB3-EDD9DBA676E9","layers":[{"animations":[],"layers":[],"texturedRectangle":{"singleTextureOpacity":1,"textXHeight":0.3483243243243243,"textBaseline":0.7290807511355426,"isBackgroundTexture":false,"isVerticalText":false,"textColor":[0.9999966025352478,0.9999999403953552,0.9999999403953552,1],"textureType":6},"initialState":{"affineTransform":[1,0,0,1,0,0],"masksToBounds":false,"rotation":0,"scale":1,"position":{"pointX":388.5,"pointY":132},"width":769,"sublayerTransform":[1,0,0,0,0,1,0,0,0,0,1,0,0,0,0,1],"contentsRect":{"y":0,"x":0,"width":1,"height":1},"opacity":1,"edgeAntialiasingMask":0,"height":74,"hidden":false,"anchorPoint":{"pointX":0.5,"pointY":0.5}},"texture":"047BA3E01BAFA95A6E2775B6BF8DBDBD"},{"animations":[],"layers":[],"texturedRectangle":{"singleTextureOpacity":1,"textXHeight":0.3483243243243243,"textBaseline":0.7290807511355426,"isBackgroundTexture":false,"isVerticalText":false,"textColor":[0.9999966025352478,0.9999999403953552,0.9999999403953552,1],"textureType":6},"initialState":{"affineTransform":[1,0,0,1,0,0],"masksToBounds":false,"rotation":0,"scale":1,"position":{"pointX":217.5,"pointY":249},"width":427,"sublayerTransform":[1,0,0,0,0,1,0,0,0,0,1,0,0,0,0,1],"contentsRect":{"y":0,"x":0,"width":1,"height":1},"opacity":1,"edgeAntialiasingMask":0,"height":74,"hidden":false,"anchorPoint":{"pointX":0.5,"pointY":0.5}},"texture":"82ABF33542CECB6A3099368921C9E819"},{"animations":[],"layers":[],"texturedRectangle":{"singleTextureOpacity":1,"textXHeight":0.3483243243243243,"textBaseline":0.7290807511355426,"isBackgroundTexture":false,"isVerticalText":false,"textColor":[0.9999966025352478,0.9999999403953552,0.9999999403953552,1],"textureType":6},"initialState":{"affineTransform":[1,0,0,1,0,0],"masksToBounds":false,"rotation":0,"scale":1,"position":{"pointX":98.5,"pointY":366},"width":189,"sublayerTransform":[1,0,0,0,0,1,0,0,0,0,1,0,0,0,0,1],"contentsRect":{"y":0,"x":0,"width":1,"height":1},"opacity":1,"edgeAntialiasingMask":0,"height":74,"hidden":false,"anchorPoint":{"pointX":0.5,"pointY":0.5}},"texture":"B7DA436456C233738E63454C42CFA678"},{"animations":[],"layers":[],"texturedRectangle":{"singleTextureOpacity":1,"textXHeight":0.3483243243243243,"textBaseline":0.7290807511355426,"isBackgroundTexture":false,"isVerticalText":false,"textColor":[0.9999966025352478,0.9999999403953552,0.9999999403953552,1],"textureType":6},"initialState":{"affineTransform":[1,0,0,1,0,0],"masksToBounds":false,"rotation":0,"scale":1,"position":{"pointX":425,"pointY":483},"width":842,"sublayerTransform":[1,0,0,0,0,1,0,0,0,0,1,0,0,0,0,1],"contentsRect":{"y":0,"x":0,"width":1,"height":1},"opacity":1,"edgeAntialiasingMask":0,"height":74,"hidden":true,"anchorPoint":{"pointX":0.5,"pointY":0.5}},"texture":"952DA6C4149651D70B7972DF03519E25"},{"animations":[],"layers":[],"texturedRectangle":{"singleTextureOpacity":1,"textXHeight":0.3483243243243243,"textBaseline":0.7290807511355426,"isBackgroundTexture":false,"isVerticalText":false,"textColor":[0.9999966025352478,0.9999999403953552,0.9999999403953552,1],"textureType":6},"initialState":{"affineTransform":[1,0,0,1,0,0],"masksToBounds":false,"rotation":0,"scale":1,"position":{"pointX":371.5,"pointY":600},"width":735,"sublayerTransform":[1,0,0,0,0,1,0,0,0,0,1,0,0,0,0,1],"contentsRect":{"y":0,"x":0,"width":1,"height":1},"opacity":1,"edgeAntialiasingMask":0,"height":74,"hidden":true,"anchorPoint":{"pointX":0.5,"pointY":0.5}},"texture":"78DCFDC79466125F556552A5C0ED4ED7"}]}]}]}},{"effects":[{"beginTime":0,"baseLayer":{"animations":[],"initialState":{"affineTransform":[1,0,0,1,0,0],"masksToBounds":false,"rotation":0,"scale":1,"position":{"pointX":554,"pointY":519},"width":842,"sublayerTransform":[1,0,0,0,0,1,0,0,0,0,1,0,0,0,0,1],"contentsRect":{"y":0,"x":0,"width":1,"height":1},"opacity":1,"edgeAntialiasingMask":251658240,"height":542,"hidden":false,"anchorPoint":{"pointX":0.5,"pointY":0.5}},"objectID":"4528A7A3-3462-44E6-9CB3-EDD9DBA676E9","layers":[{"animations":[],"layers":[],"texturedRectangle":{"singleTextureOpacity":1,"textXHeight":0.3483243243243243,"textBaseline":0.7290807511355426,"isBackgroundTexture":false,"isVerticalText":false,"textColor":[0.9999966025352478,0.9999999403953552,0.9999999403953552,1],"textureType":6},"initialState":{"affineTransform":[1,0,0,1,0,0],"masksToBounds":false,"rotation":0,"scale":1,"position":{"pointX":388.5,"pointY":132},"width":769,"sublayerTransform":[1,0,0,0,0,1,0,0,0,0,1,0,0,0,0,1],"contentsRect":{"y":0,"x":0,"width":1,"height":1},"opacity":1,"edgeAntialiasingMask":0,"height":74,"hidden":false,"anchorPoint":{"pointX":0.5,"pointY":0.5}},"texture":"047BA3E01BAFA95A6E2775B6BF8DBDBD"},{"animations":[],"layers":[],"texturedRectangle":{"singleTextureOpacity":1,"textXHeight":0.3483243243243243,"textBaseline":0.7290807511355426,"isBackgroundTexture":false,"isVerticalText":false,"textColor":[0.9999966025352478,0.9999999403953552,0.9999999403953552,1],"textureType":6},"initialState":{"affineTransform":[1,0,0,1,0,0],"masksToBounds":false,"rotation":0,"scale":1,"position":{"pointX":217.5,"pointY":249},"width":427,"sublayerTransform":[1,0,0,0,0,1,0,0,0,0,1,0,0,0,0,1],"contentsRect":{"y":0,"x":0,"width":1,"height":1},"opacity":1,"edgeAntialiasingMask":0,"height":74,"hidden":false,"anchorPoint":{"pointX":0.5,"pointY":0.5}},"texture":"82ABF33542CECB6A3099368921C9E819"},{"animations":[],"layers":[],"texturedRectangle":{"singleTextureOpacity":1,"textXHeight":0.3483243243243243,"textBaseline":0.7290807511355426,"isBackgroundTexture":false,"isVerticalText":false,"textColor":[0.9999966025352478,0.9999999403953552,0.9999999403953552,1],"textureType":6},"initialState":{"affineTransform":[1,0,0,1,0,0],"masksToBounds":false,"rotation":0,"scale":1,"position":{"pointX":98.5,"pointY":366},"width":189,"sublayerTransform":[1,0,0,0,0,1,0,0,0,0,1,0,0,0,0,1],"contentsRect":{"y":0,"x":0,"width":1,"height":1},"opacity":1,"edgeAntialiasingMask":0,"height":74,"hidden":false,"anchorPoint":{"pointX":0.5,"pointY":0.5}},"texture":"B7DA436456C233738E63454C42CFA678"},{"animations":[],"layers":[],"texturedRectangle":{"singleTextureOpacity":1,"textXHeight":0.3483243243243243,"textBaseline":0.7290807511355426,"isBackgroundTexture":false,"isVerticalText":false,"textColor":[0.9999966025352478,0.9999999403953552,0.9999999403953552,1],"textureType":6},"initialState":{"affineTransform":[1,0,0,1,0,0],"masksToBounds":false,"rotation":0,"scale":1,"position":{"pointX":425,"pointY":483},"width":842,"sublayerTransform":[1,0,0,0,0,1,0,0,0,0,1,0,0,0,0,1],"contentsRect":{"y":0,"x":0,"width":1,"height":1},"opacity":1,"edgeAntialiasingMask":0,"height":74,"hidden":false,"anchorPoint":{"pointX":0.5,"pointY":0.5}},"texture":"952DA6C4149651D70B7972DF03519E25"},{"animations":[],"initialState":{"affineTransform":[1,0,0,1,0,0],"masksToBounds":false,"rotation":0,"scale":1,"position":{"pointX":827,"pointY":292},"width":842,"sublayerTransform":[1,0,0,0,0,1,0,0,0,0,1,-0.0003500791246677598,0,0,0,1],"contentsRect":{"y":0,"x":0,"width":1,"height":1},"opacity":1,"edgeAntialiasingMask":251658240,"height":542,"hidden":false,"anchorPoint":{"pointX":0.9821852731591449,"pointY":0.5387453874538746}},"layers":[{"animations":[{"timeOffset":0,"beginTime":1e-100,"animations":[{"timeOffset":0,"from":{"scalar":0},"beginTime":0,"repeatCount":0,"fillMode":"both","duration":1,"autoreverses":false,"timingFunction":"EaseInEaseOut","property":"opacity","to":{"scalar":1}},{"timeOffset":0,"from":{"scalar":false},"beginTime":0,"repeatCount":0,"fillMode":"forwards","property":"hidden","autoreverses":false,"duration":1,"to":{"scalar":false}}],"repeatCount":0,"duration":1,"autoreverses":false,"fillMode":"both"}],"layers":[],"texturedRectangle":{"singleTextureOpacity":1,"textXHeight":0.3483243243243243,"textBaseline":0.7290807511355426,"isBackgroundTexture":false,"isVerticalText":false,"textColor":[0.9999966025352478,0.9999999403953552,0.9999999403953552,1],"textureType":6},"initialState":{"affineTransform":[1,0,0,1,0,0],"masksToBounds":false,"rotation":0,"scale":1,"position":{"pointX":371.5,"pointY":600},"width":735,"sublayerTransform":[1,0,0,0,0,1,0,0,0,0,1,0,0,0,0,1],"contentsRect":{"y":0,"x":0,"width":1,"height":1},"opacity":1,"edgeAntialiasingMask":0,"height":74,"hidden":true,"anchorPoint":{"pointX":0.5,"pointY":0.5}},"texture":"78DCFDC79466125F556552A5C0ED4ED7"}]}]},"effects":[],"duration":1,"type":"buildIn","name":"apple:dissolve character","objectID":"4528A7A3-3462-44E6-9CB3-EDD9DBA676E9"}],"automaticPlay":false,"hyperlinks":[],"accessibility":[{"text":"Support public, blame private","targetRectangle":{"y":351,"x":186.9999980926514,"width":718.3680000000002,"height":58}},{"text":"Admit mistakes","targetRectangle":{"y":409,"x":186.9999980926514,"width":376.6079999999999,"height":117}},{"text":"Listen","targetRectangle":{"y":526,"x":186.9999980926514,"width":141.12,"height":117}},{"text":"Offer alternatives while declining","targetRectangle":{"y":643,"x":186.9999980926514,"width":793.5839999999998,"height":117}},{"text":"Avoid Being an @sshole","targetRectangle":{"y":50,"x":291.864,"width":1336.272,"height":136}}],"baseLayer":{"animations":[],"initialState":{"affineTransform":[1,0,0,1,0,0],"masksToBounds":false,"rotation":0,"scale":1,"position":{"pointX":960,"pointY":540},"width":1920,"sublayerTransform":[1,0,0,0,0,1,0,0,0,0,1,0,0,0,0,1],"contentsRect":{"y":0,"x":0,"width":1,"height":1},"opacity":1,"edgeAntialiasingMask":251658240,"height":1080,"hidden":false,"anchorPoint":{"pointX":0.5,"pointY":0.5}},"layers":[{"animations":[],"initialState":{"affineTransform":[1,0,0,1,0,0],"masksToBounds":false,"rotation":0,"scale":1,"position":{"pointX":960,"pointY":540},"width":1920,"sublayerTransform":[1,0,0,0,0,1,0,0,0,0,1,0,0,0,0,1],"contentsRect":{"y":0,"x":0,"width":1,"height":1},"opacity":1,"edgeAntialiasingMask":251658240,"height":1080,"hidden":false,"anchorPoint":{"pointX":0.5,"pointY":0.5}},"layers":[{"animations":[],"initialState":{"affineTransform":[1,0,0,1,0,0],"masksToBounds":false,"rotation":0,"scale":1,"position":{"pointX":960,"pointY":540},"width":1920,"sublayerTransform":[1,0,0,0,0,1,0,0,0,0,1,0,0,0,0,1],"contentsRect":{"y":0,"x":0,"width":1,"height":1},"opacity":1,"edgeAntialiasingMask":251658240,"height":1080,"hidden":false,"anchorPoint":{"pointX":0.5,"pointY":0.5}},"layers":[{"animations":[],"layers":[],"texturedRectangle":{"isBackgroundTexture":true,"singleTextureOpacity":1,"textureType":1,"textBaseline":0,"textXHeight":0,"isVerticalText":false},"initialState":{"affineTransform":[1,0,0,1,0,0],"masksToBounds":false,"rotation":0,"scale":1,"position":{"pointX":960,"pointY":540},"width":1920,"sublayerTransform":[1,0,0,0,0,1,0,0,0,0,1,0,0,0,0,1],"contentsRect":{"y":0,"x":0,"width":1,"height":1},"opacity":1,"edgeAntialiasingMask":0,"height":1080,"hidden":false,"anchorPoint":{"pointX":0.5,"pointY":0.5}},"texture":"ACD8C7F538D7B6317F7256BC3826AC83"}]}]},{"animations":[],"initialState":{"affineTransform":[1,0,0,1,0,0],"masksToBounds":false,"rotation":0,"scale":1,"position":{"pointX":960,"pointY":540},"width":1920,"sublayerTransform":[1,0,0,0,0,1,0,0,0,0,1,0,0,0,0,1],"contentsRect":{"y":0,"x":0,"width":1,"height":1},"opacity":1,"edgeAntialiasingMask":251658240,"height":1080,"hidden":false,"anchorPoint":{"pointX":0.5,"pointY":0.5}},"layers":[{"animations":[],"initialState":{"affineTransform":[1,0,0,1,0,0],"masksToBounds":false,"rotation":0,"scale":1,"position":{"pointX":801.5,"pointY":83},"width":1337,"sublayerTransform":[1,0,0,0,0,1,0,0,0,0,1,0,0,0,0,1],"contentsRect":{"y":0,"x":0,"width":1,"height":1},"opacity":1,"edgeAntialiasingMask":251658240,"height":110,"hidden":false,"anchorPoint":{"pointX":0.5,"pointY":0.5}},"layers":[{"animations":[],"layers":[],"texturedRectangle":{"singleTextureOpacity":1,"textXHeight":0.5467636363636363,"textBaseline":0.7807994820854881,"isBackgroundTexture":true,"isVerticalText":false,"textColor":[0.9999966025352478,0.9999999403953552,0.9999999403953552,1],"textureType":6},"initialState":{"affineTransform":[1,0,0,1,0,0],"masksToBounds":false,"rotation":0,"scale":1,"position":{"pointX":825.5,"pointY":99},"width":1337,"sublayerTransform":[1,0,0,0,0,1,0,0,0,0,1,0,0,0,0,1],"contentsRect":{"y":0,"x":0,"width":1,"height":1},"opacity":1,"edgeAntialiasingMask":0,"height":110,"hidden":false,"anchorPoint":{"pointX":0.5,"pointY":0.5}},"texture":"CB56F0B3CF82F58DD490AF351BAAFC86"}]}]},{"animations":[],"initialState":{"affineTransform":[1,0,0,1,0,0],"masksToBounds":false,"rotation":0,"scale":1,"position":{"pointX":960,"pointY":540},"width":1920,"sublayerTransform":[1,0,0,0,0,1,0,0,0,0,1,0,0,0,0,1],"contentsRect":{"y":0,"x":0,"width":1,"height":1},"opacity":1,"edgeAntialiasingMask":251658240,"height":1080,"hidden":false,"anchorPoint":{"pointX":0.5,"pointY":0.5}},"layers":[{"animations":[],"initialState":{"affineTransform":[1,0,0,1,0,0],"masksToBounds":false,"rotation":0,"scale":1,"position":{"pointX":554,"pointY":519},"width":842,"sublayerTransform":[1,0,0,0,0,1,0,0,0,0,1,0,0,0,0,1],"contentsRect":{"y":0,"x":0,"width":1,"height":1},"opacity":1,"edgeAntialiasingMask":251658240,"height":542,"hidden":false,"anchorPoint":{"pointX":0.5,"pointY":0.5}},"objectID":"4528A7A3-3462-44E6-9CB3-EDD9DBA676E9","layers":[{"animations":[],"layers":[],"texturedRectangle":{"singleTextureOpacity":1,"textXHeight":0.3483243243243243,"textBaseline":0.7290807511355426,"isBackgroundTexture":false,"isVerticalText":false,"textColor":[0.9999966025352478,0.9999999403953552,0.9999999403953552,1],"textureType":6},"initialState":{"affineTransform":[1,0,0,1,0,0],"masksToBounds":false,"rotation":0,"scale":1,"position":{"pointX":388.5,"pointY":132},"width":769,"sublayerTransform":[1,0,0,0,0,1,0,0,0,0,1,0,0,0,0,1],"contentsRect":{"y":0,"x":0,"width":1,"height":1},"opacity":1,"edgeAntialiasingMask":0,"height":74,"hidden":false,"anchorPoint":{"pointX":0.5,"pointY":0.5}},"texture":"047BA3E01BAFA95A6E2775B6BF8DBDBD"},{"animations":[],"layers":[],"texturedRectangle":{"singleTextureOpacity":1,"textXHeight":0.3483243243243243,"textBaseline":0.7290807511355426,"isBackgroundTexture":false,"isVerticalText":false,"textColor":[0.9999966025352478,0.9999999403953552,0.9999999403953552,1],"textureType":6},"initialState":{"affineTransform":[1,0,0,1,0,0],"masksToBounds":false,"rotation":0,"scale":1,"position":{"pointX":217.5,"pointY":249},"width":427,"sublayerTransform":[1,0,0,0,0,1,0,0,0,0,1,0,0,0,0,1],"contentsRect":{"y":0,"x":0,"width":1,"height":1},"opacity":1,"edgeAntialiasingMask":0,"height":74,"hidden":false,"anchorPoint":{"pointX":0.5,"pointY":0.5}},"texture":"82ABF33542CECB6A3099368921C9E819"},{"animations":[],"layers":[],"texturedRectangle":{"singleTextureOpacity":1,"textXHeight":0.3483243243243243,"textBaseline":0.7290807511355426,"isBackgroundTexture":false,"isVerticalText":false,"textColor":[0.9999966025352478,0.9999999403953552,0.9999999403953552,1],"textureType":6},"initialState":{"affineTransform":[1,0,0,1,0,0],"masksToBounds":false,"rotation":0,"scale":1,"position":{"pointX":98.5,"pointY":366},"width":189,"sublayerTransform":[1,0,0,0,0,1,0,0,0,0,1,0,0,0,0,1],"contentsRect":{"y":0,"x":0,"width":1,"height":1},"opacity":1,"edgeAntialiasingMask":0,"height":74,"hidden":false,"anchorPoint":{"pointX":0.5,"pointY":0.5}},"texture":"B7DA436456C233738E63454C42CFA678"},{"animations":[],"layers":[],"texturedRectangle":{"singleTextureOpacity":1,"textXHeight":0.3483243243243243,"textBaseline":0.7290807511355426,"isBackgroundTexture":false,"isVerticalText":false,"textColor":[0.9999966025352478,0.9999999403953552,0.9999999403953552,1],"textureType":6},"initialState":{"affineTransform":[1,0,0,1,0,0],"masksToBounds":false,"rotation":0,"scale":1,"position":{"pointX":425,"pointY":483},"width":842,"sublayerTransform":[1,0,0,0,0,1,0,0,0,0,1,0,0,0,0,1],"contentsRect":{"y":0,"x":0,"width":1,"height":1},"opacity":1,"edgeAntialiasingMask":0,"height":74,"hidden":false,"anchorPoint":{"pointX":0.5,"pointY":0.5}},"texture":"952DA6C4149651D70B7972DF03519E25"},{"animations":[],"layers":[],"texturedRectangle":{"singleTextureOpacity":1,"textXHeight":0.3483243243243243,"textBaseline":0.7290807511355426,"isBackgroundTexture":false,"isVerticalText":false,"textColor":[0.9999966025352478,0.9999999403953552,0.9999999403953552,1],"textureType":6},"initialState":{"affineTransform":[1,0,0,1,0,0],"masksToBounds":false,"rotation":0,"scale":1,"position":{"pointX":371.5,"pointY":600},"width":735,"sublayerTransform":[1,0,0,0,0,1,0,0,0,0,1,0,0,0,0,1],"contentsRect":{"y":0,"x":0,"width":1,"height":1},"opacity":1,"edgeAntialiasingMask":0,"height":74,"hidden":true,"anchorPoint":{"pointX":0.5,"pointY":0.5}},"texture":"78DCFDC79466125F556552A5C0ED4ED7"}]}]}]}},{"effects":[{"beginTime":0,"baseLayer":{"animations":[],"initialState":{"affineTransform":[1,0,0,1,0,0],"masksToBounds":false,"rotation":0,"scale":1,"position":{"pointX":960,"pointY":540},"width":1920,"sublayerTransform":[1,0,0,0,0,1,0,0,0,0,1,0,0,0,0,1],"contentsRect":{"y":0,"x":0,"width":1,"height":1},"opacity":1,"edgeAntialiasingMask":251658240,"height":1080,"hidden":false,"anchorPoint":{"pointX":0.5,"pointY":0.5}},"objectID":"0","layers":[{"animations":[],"initialState":{"affineTransform":[1,0,0,1,0,0],"masksToBounds":false,"rotation":0,"scale":1,"position":{"pointX":960,"pointY":540},"width":1920,"sublayerTransform":[1,0,0,0,0,1,0,0,0,0,1,-0.0003500791246677598,0,0,0,1],"contentsRect":{"y":0,"x":0,"width":1,"height":1},"opacity":1,"edgeAntialiasingMask":251658240,"height":1080,"hidden":false,"anchorPoint":{"pointX":0.5,"pointY":0.5}},"layers":[{"animations":[],"layers":[],"texturedRectangle":{"isBackgroundTexture":false,"singleTextureOpacity":1,"textureType":0,"textBaseline":0,"textXHeight":0,"isVerticalText":false},"initialState":{"affineTransform":[1,0,0,1,0,0],"masksToBounds":false,"rotation":0,"scale":1,"position":{"pointX":960,"pointY":540},"width":1920,"sublayerTransform":[1,0,0,0,0,1,0,0,0,0,1,0,0,0,0,1],"contentsRect":{"y":0,"x":0,"width":1,"height":1},"opacity":1,"edgeAntialiasingMask":0,"height":1080,"hidden":false,"anchorPoint":{"pointX":0.5,"pointY":0.5}},"texture":"D130F2C8C682871CE1E548A91CC54928"},{"animations":[{"timeOffset":0,"from":{"scalar":false},"beginTime":0,"repeatCount":0,"fillMode":"both","property":"hidden","autoreverses":false,"duration":0.01,"to":{"scalar":true}}],"layers":[],"texturedRectangle":{"isBackgroundTexture":false,"singleTextureOpacity":1,"textureType":0,"textBaseline":0,"textXHeight":0,"isVerticalText":false},"initialState":{"affineTransform":[1,0,0,1,0,0],"masksToBounds":false,"rotation":0,"scale":1,"position":{"pointX":960,"pointY":540},"width":1920,"sublayerTransform":[1,0,0,0,0,1,0,0,0,0,1,0,0,0,0,1],"contentsRect":{"y":0,"x":0,"width":1,"height":1},"opacity":1,"edgeAntialiasingMask":0,"height":1080,"hidden":false,"anchorPoint":{"pointX":0.5,"pointY":0.5}},"texture":"E4ED9C930350BFB2E06DD59A2760DFAA"}]}]},"effects":[],"duration":0.01,"type":"transition","name":"none","objectID":"0"}],"automaticPlay":false,"hyperlinks":[],"accessibility":[{"text":"Support public, blame private","targetRectangle":{"y":351,"x":186.9999980926514,"width":718.3680000000002,"height":58}},{"text":"Admit mistakes","targetRectangle":{"y":409,"x":186.9999980926514,"width":376.6079999999999,"height":117}},{"text":"Listen","targetRectangle":{"y":526,"x":186.9999980926514,"width":141.12,"height":117}},{"text":"Offer alternatives while declining","targetRectangle":{"y":643,"x":186.9999980926514,"width":793.5839999999998,"height":117}},{"text":"Don't put people in pressure","targetRectangle":{"y":760,"x":186.9999980926514,"width":684.3840000000001,"height":117}},{"text":"Avoid Being an @sshole","targetRectangle":{"y":50,"x":291.864,"width":1336.272,"height":136}}],"baseLayer":{"animations":[],"initialState":{"affineTransform":[1,0,0,1,0,0],"masksToBounds":false,"rotation":0,"scale":1,"position":{"pointX":960,"pointY":540},"width":1920,"sublayerTransform":[1,0,0,0,0,1,0,0,0,0,1,0,0,0,0,1],"contentsRect":{"y":0,"x":0,"width":1,"height":1},"opacity":1,"edgeAntialiasingMask":251658240,"height":1080,"hidden":false,"anchorPoint":{"pointX":0.5,"pointY":0.5}},"objectID":"0","layers":[{"animations":[],"initialState":{"affineTransform":[1,0,0,1,0,0],"masksToBounds":false,"rotation":0,"scale":1,"position":{"pointX":960,"pointY":540},"width":1920,"sublayerTransform":[1,0,0,0,0,1,0,0,0,0,1,-0.0003500791246677598,0,0,0,1],"contentsRect":{"y":0,"x":0,"width":1,"height":1},"opacity":1,"edgeAntialiasingMask":251658240,"height":1080,"hidden":false,"anchorPoint":{"pointX":0.5,"pointY":0.5}},"layers":[{"animations":[],"layers":[],"texturedRectangle":{"isBackgroundTexture":false,"singleTextureOpacity":1,"textureType":0,"textBaseline":0,"textXHeight":0,"isVerticalText":false},"initialState":{"affineTransform":[1,0,0,1,0,0],"masksToBounds":false,"rotation":0,"scale":1,"position":{"pointX":960,"pointY":540},"width":1920,"sublayerTransform":[1,0,0,0,0,1,0,0,0,0,1,0,0,0,0,1],"contentsRect":{"y":0,"x":0,"width":1,"height":1},"opacity":1,"edgeAntialiasingMask":0,"height":1080,"hidden":false,"anchorPoint":{"pointX":0.5,"pointY":0.5}},"texture":"E4ED9C930350BFB2E06DD59A2760DFAA"}]}]}}]}